{"enunciado":"1 - O que o Brasil será em 2018?","alternativas":["a. Penta","b. Hexa","c. Comunista","d. Octa"],"resposta":"1"}
{"enunciado":"2 - Qual o nome do mascote do Brasil nas copas?","alternativas":["a. Leãozito","b. Canarinho putasso","c. Gatinho","d. Matadorzinho de alemón"],"resposta":"1"}
{"enunciado":"3 - Quem é o melhor jogador do mundo atualmente? (sem clubismo)","alternativas":["a. Lewandovski","b. CR7","c. Valdivia poko pika","d. Suárez"],"resposta":"2"}
{"enunciado":"4 - Quem o Brasil tá mais com sangue no zói pra destruir em 2018?","alternativas":["a. Itália","b. França","c. Alemanha","d. Canadá"],"resposta":"2"}
{"enunciado":"5 - Qual o nome do jogador mais humilde das olimpíadas de 2016?","alternativas":["a. Neymar","b. Rodrigo Caio","c. Luan","d. Glória, glória, Gabriel Jesus (esse)"],"resposta":"3"}
